{
"meta":{"test_sets":[],"test_metrics":[],"learn_metrics":[{"best_value":"Min","name":"RMSE"}],"launch_mode":"Train","parameters":"","iteration_count":100,"learn_sets":["learn"],"name":"experiment"},
"iterations":[
{"learn":[13.96962521],"iteration":0,"passed_time":0.002827945465,"remaining_time":0.279966601},
{"learn":[13.09082657],"iteration":1,"passed_time":0.004498905719,"remaining_time":0.2204463802},
{"learn":[12.27861651],"iteration":2,"passed_time":0.006131780009,"remaining_time":0.198260887},
{"learn":[11.53029884],"iteration":3,"passed_time":0.007750067546,"remaining_time":0.1860016211},
{"learn":[10.87492512],"iteration":4,"passed_time":0.009464477278,"remaining_time":0.1798250683},
{"learn":[10.38155225],"iteration":5,"passed_time":0.0110418818,"remaining_time":0.1729894816},
{"learn":[9.857621344],"iteration":6,"passed_time":0.01265663042,"remaining_time":0.1681523756},
{"learn":[9.411181059],"iteration":7,"passed_time":0.01443053005,"remaining_time":0.1659510956},
{"learn":[8.998198398],"iteration":8,"passed_time":0.01624471117,"remaining_time":0.1642520796},
{"learn":[8.588034504],"iteration":9,"passed_time":0.01784688812,"remaining_time":0.160621993},
{"learn":[8.232135915],"iteration":10,"passed_time":0.01942343047,"remaining_time":0.1571532102},
{"learn":[7.936645968],"iteration":11,"passed_time":0.02104746248,"remaining_time":0.1543480582},
{"learn":[7.686327869],"iteration":12,"passed_time":0.02257622444,"remaining_time":0.1510870405},
{"learn":[7.453139483],"iteration":13,"passed_time":0.02441937857,"remaining_time":0.150004754},
{"learn":[7.216574456],"iteration":14,"passed_time":0.0262426927,"remaining_time":0.148708592},
{"learn":[7.018377399],"iteration":15,"passed_time":0.0279298638,"remaining_time":0.1466317849},
{"learn":[6.823313325],"iteration":16,"passed_time":0.0299609314,"remaining_time":0.1462798416},
{"learn":[6.666946823],"iteration":17,"passed_time":0.03178520796,"remaining_time":0.1447992807},
{"learn":[6.508910347],"iteration":18,"passed_time":0.03340054807,"remaining_time":0.1423918102},
{"learn":[6.386746007],"iteration":19,"passed_time":0.03512259705,"remaining_time":0.1404903882},
{"learn":[6.265973887],"iteration":20,"passed_time":0.03793032157,"remaining_time":0.1426902573},
{"learn":[6.169088554],"iteration":21,"passed_time":0.039861307,"remaining_time":0.1413264521},
{"learn":[6.063254647],"iteration":22,"passed_time":0.04158028825,"remaining_time":0.1392035737},
{"learn":[5.976012341],"iteration":23,"passed_time":0.04322536328,"remaining_time":0.1368803171},
{"learn":[5.901135024],"iteration":24,"passed_time":0.04516755695,"remaining_time":0.1355026708},
{"learn":[5.835939901],"iteration":25,"passed_time":0.04676977399,"remaining_time":0.1331139721},
{"learn":[5.775227205],"iteration":26,"passed_time":0.04840613708,"remaining_time":0.1308758521},
{"learn":[5.723443194],"iteration":27,"passed_time":0.05012111825,"remaining_time":0.1288828755},
{"learn":[5.680032138],"iteration":28,"passed_time":0.05196041265,"remaining_time":0.1272134241},
{"learn":[5.627248312],"iteration":29,"passed_time":0.05359612409,"remaining_time":0.1250576229},
{"learn":[5.592690321],"iteration":30,"passed_time":0.05517737831,"remaining_time":0.1228141646},
{"learn":[5.544273978],"iteration":31,"passed_time":0.05677812164,"remaining_time":0.1206535085},
{"learn":[5.503344158],"iteration":32,"passed_time":0.05839623875,"remaining_time":0.1185620605},
{"learn":[5.478259921],"iteration":33,"passed_time":0.06039638845,"remaining_time":0.1172400482},
{"learn":[5.442185155],"iteration":34,"passed_time":0.06206657676,"remaining_time":0.1152664997},
{"learn":[5.407844279],"iteration":35,"passed_time":0.06369328551,"remaining_time":0.1132325076},
{"learn":[5.383507306],"iteration":36,"passed_time":0.06535571427,"remaining_time":0.1112813513},
{"learn":[5.362378839],"iteration":37,"passed_time":0.06696611193,"remaining_time":0.1092604984},
{"learn":[5.340630083],"iteration":38,"passed_time":0.06860585352,"remaining_time":0.1073065914},
{"learn":[5.318674311],"iteration":39,"passed_time":0.0702006218,"remaining_time":0.1053009327},
{"learn":[5.302066897],"iteration":40,"passed_time":0.07179843775,"remaining_time":0.1033197031},
{"learn":[5.284928558],"iteration":41,"passed_time":0.07347801973,"remaining_time":0.1014696463},
{"learn":[5.272330995],"iteration":42,"passed_time":0.07536435265,"remaining_time":0.09990158375},
{"learn":[5.261014227],"iteration":43,"passed_time":0.07647823927,"remaining_time":0.09733594089},
{"learn":[5.229469639],"iteration":44,"passed_time":0.07820556153,"remaining_time":0.09558457521},
{"learn":[5.215020572],"iteration":45,"passed_time":0.07982447064,"remaining_time":0.09370698727},
{"learn":[5.193062414],"iteration":46,"passed_time":0.08146988653,"remaining_time":0.09187029757},
{"learn":[5.180484848],"iteration":47,"passed_time":0.08308914652,"remaining_time":0.09001324206},
{"learn":[5.165159502],"iteration":48,"passed_time":0.08470156927,"remaining_time":0.08815877618},
{"learn":[5.141982763],"iteration":49,"passed_time":0.08639759268,"remaining_time":0.08639759268},
{"learn":[5.131085119],"iteration":50,"passed_time":0.0880767135,"remaining_time":0.08462272473},
{"learn":[5.115896901],"iteration":51,"passed_time":0.08984717446,"remaining_time":0.08293585335},
{"learn":[5.102227813],"iteration":52,"passed_time":0.09145867489,"remaining_time":0.08110486264},
{"learn":[5.092694221],"iteration":53,"passed_time":0.09321151145,"remaining_time":0.07940239864},
{"learn":[5.084135611],"iteration":54,"passed_time":0.09485656643,"remaining_time":0.07760991799},
{"learn":[5.067392027],"iteration":55,"passed_time":0.09652335617,"remaining_time":0.07583977985},
{"learn":[5.05548496],"iteration":56,"passed_time":0.09812099168,"remaining_time":0.07402109898},
{"learn":[5.037754059],"iteration":57,"passed_time":0.09973959,"remaining_time":0.07222522034},
{"learn":[5.018441657],"iteration":58,"passed_time":0.1013808655,"remaining_time":0.07045110989},
{"learn":[5.009952596],"iteration":59,"passed_time":0.1031576524,"remaining_time":0.06877176824},
{"learn":[5.000684433],"iteration":60,"passed_time":0.1048346177,"remaining_time":0.06702541134},
{"learn":[4.982819001],"iteration":61,"passed_time":0.1065038637,"remaining_time":0.06527656161},
{"learn":[4.966552282],"iteration":62,"passed_time":0.1081256801,"remaining_time":0.06350238355},
{"learn":[4.948387795],"iteration":63,"passed_time":0.1097952869,"remaining_time":0.06175984891},
{"learn":[4.933079332],"iteration":64,"passed_time":0.1114491541,"remaining_time":0.06001108299},
{"learn":[4.923067166],"iteration":65,"passed_time":0.1131111217,"remaining_time":0.05826936574},
{"learn":[4.91587203],"iteration":66,"passed_time":0.1147941925,"remaining_time":0.05654042317},
{"learn":[4.906625327],"iteration":67,"passed_time":0.1164711779,"remaining_time":0.05480996609},
{"learn":[4.895848666],"iteration":68,"passed_time":0.1182587821,"remaining_time":0.05313075717},
{"learn":[4.886562569],"iteration":69,"passed_time":0.119982385,"remaining_time":0.05142102214},
{"learn":[4.876525557],"iteration":70,"passed_time":0.1220663358,"remaining_time":0.04985808083},
{"learn":[4.866771122],"iteration":71,"passed_time":0.1241280028,"remaining_time":0.04827200111},
{"learn":[4.860489381],"iteration":72,"passed_time":0.1258440367,"remaining_time":0.04654505466},
{"learn":[4.846895943],"iteration":73,"passed_time":0.1275143954,"remaining_time":0.04480235514},
{"learn":[4.830532583],"iteration":74,"passed_time":0.1292788412,"remaining_time":0.04309294707},
{"learn":[4.818616331],"iteration":75,"passed_time":0.1309343225,"remaining_time":0.04134768078},
{"learn":[4.806132466],"iteration":76,"passed_time":0.1328549495,"remaining_time":0.03968394595},
{"learn":[4.800479202],"iteration":77,"passed_time":0.1345335289,"remaining_time":0.03794535432},
{"learn":[4.797819002],"iteration":78,"passed_time":0.1356205078,"remaining_time":0.03605102105},
{"learn":[4.786614428],"iteration":79,"passed_time":0.1372514873,"remaining_time":0.03431287182},
{"learn":[4.777804595],"iteration":80,"passed_time":0.1388566618,"remaining_time":0.03257131572},
{"learn":[4.767203373],"iteration":81,"passed_time":0.1404738064,"remaining_time":0.03083571361},
{"learn":[4.752577047],"iteration":82,"passed_time":0.142166702,"remaining_time":0.02911848112},
{"learn":[4.743678884],"iteration":83,"passed_time":0.1437726384,"remaining_time":0.02738526445},
{"learn":[4.737404981],"iteration":84,"passed_time":0.1453826751,"remaining_time":0.0256557662},
{"learn":[4.728022428],"iteration":85,"passed_time":0.1472067612,"remaining_time":0.02396389136},
{"learn":[4.723347156],"iteration":86,"passed_time":0.1489273766,"remaining_time":0.02225351604},
{"learn":[4.717517757],"iteration":87,"passed_time":0.150494044,"remaining_time":0.0205219151},
{"learn":[4.709503034],"iteration":88,"passed_time":0.1520347762,"remaining_time":0.01879081503},
{"learn":[4.703039995],"iteration":89,"passed_time":0.1535969523,"remaining_time":0.01706632803},
{"learn":[4.696059284],"iteration":90,"passed_time":0.155254178,"remaining_time":0.01535480881},
{"learn":[4.686066202],"iteration":91,"passed_time":0.1568172764,"remaining_time":0.01363628491},
{"learn":[4.674543063],"iteration":92,"passed_time":0.1583457276,"remaining_time":0.01191849563},
{"learn":[4.671858724],"iteration":93,"passed_time":0.1599283931,"remaining_time":0.0102081953},
{"learn":[4.6586434],"iteration":94,"passed_time":0.1616145917,"remaining_time":0.008506031144},
{"learn":[4.650850795],"iteration":95,"passed_time":0.1631913948,"remaining_time":0.006799641448},
{"learn":[4.647951816],"iteration":96,"passed_time":0.1647140313,"remaining_time":0.00509424839},
{"learn":[4.636294688],"iteration":97,"passed_time":0.166322083,"remaining_time":0.003394328225},
{"learn":[4.629521481],"iteration":98,"passed_time":0.1679256735,"remaining_time":0.001696218925},
{"learn":[4.625948565],"iteration":99,"passed_time":0.1694484805,"remaining_time":0}
]}